[
  {
    "title": "9个项目助你在2020年成为前端大师！",
    "description": "DEV的年度热文，读完觉得不错，所以翻译出来供大家参考，个人水平有限，文中可能会有一些翻译错误，可以在评论区指正。",
    "url": "https://segmentfault.com/a/1190000020907687",
    "author": "刘小夕",
    "home_url": "https://segmentfault.com/u/liuyan666",
    "votes": "213",
    "rank": 1
  },
  {
    "title": "前端与算法 leetcode 350. 两个数组的交集 II",
    "description": "[TOC] 前端与算法 leetcode 350. 两个数组的交集 II 题目描述 给定两个数组，编写一个函数来计算它们的交集。 示例 1: {代码...} 示例 2: {代码...} 说明： 输出结果中每个元素出现的次数，应与元素在两个数组中...",
    "url": "https://segmentfault.com/a/1190000020957484",
    "author": "墨抒颖",
    "home_url": "https://segmentfault.com/u/moshuying",
    "votes": "2",
    "rank": 2
  },
  {
    "title": "灵活运用CSS开发技巧(66个实用技巧，值得收藏)",
    "description": "何为技巧，意指表现在文学、工艺、体育等方面的巧妙技能。代码作为一门现代高级工艺，推动着人类科学技术的发展，同时犹如文字一样承托着人类文化的进步。",
    "url": "https://segmentfault.com/a/1190000020899202",
    "author": "JowayYoung",
    "home_url": "https://segmentfault.com/u/yangzw",
    "votes": "164",
    "rank": 3
  },
  {
    "title": "vue的provide / inject 有什么用？",
    "description": "vue的父子组件通信用什么？：prop和$emit的组合。如果是爷孙组件呢？：那么就要用父组件来转发数据和事件了。如果是太爷爷和孙子组件呢？：当然是vuex啦emmm 好的，没我啥事了，我这就走。",
    "url": "https://segmentfault.com/a/1190000020954324",
    "author": "李大雷",
    "home_url": "https://segmentfault.com/u/lidalei",
    "votes": "10",
    "rank": 4
  },
  {
    "title": "灵活运用PS切图技巧",
    "description": "话说，以前的前端工程师在入行时都当过切图仔或切图女。曾经，切图作为前端一门基础且必备的技能，不知何时开始已经不再提起。很多面试官在招聘时都忽略了PS的存在，其实在国外一位优秀的前端工程师是包揽设计工...",
    "url": "https://segmentfault.com/a/1190000020936896",
    "author": "JowayYoung",
    "home_url": "https://segmentfault.com/u/yangzw",
    "votes": "25",
    "rank": 5
  },
  {
    "title": "vue表单校验 100行小白自编",
    "description": "两个文件，一个写逻辑，一个写校验规则；特点：逻辑简单，代码量少，够用；不想看代码直接新建这两个文件复制代码，看最下面的使用方法；示例图片",
    "url": "https://segmentfault.com/a/1190000020937289",
    "author": "liubingyang",
    "home_url": "https://segmentfault.com/u/liubingyang_5aa7319fed77d",
    "votes": "14",
    "rank": 6
  },
  {
    "title": "完全搞懂 Javascript 中的...",
    "description": "曾几何时，ES6/ES2015 对 Javascript 语言进行了重大升级。它引入了许多不同的新功能。其中之一就是我们可以用在任何兼容容器（对象、数组、字符串、集合、映射）前面的三个连续点。这些小点使我们能够编写更加优...",
    "url": "https://segmentfault.com/a/1190000020947074",
    "author": "疯狂的技术宅",
    "home_url": "https://segmentfault.com/u/evilboy",
    "votes": "16",
    "rank": 7
  },
  {
    "title": "35 道咱们必须要清楚的 React 面试题",
    "description": "上个月自己花了 1300 买了阿里的服务器来学习 node 及对应的框架，在 11 号之前它们有做活动，1300 的配置现在一年只要 86 元，三年只要229元，真心觉得很划算了，可以点击下面链接进行参与:",
    "url": "https://segmentfault.com/a/1190000020912300",
    "author": "前端小智",
    "home_url": "https://segmentfault.com/u/minnanitkong",
    "votes": "45",
    "rank": 8
  },
  {
    "title": "这些前端资源，你值得拥有",
    "description": "<!-- @Author: Rainy @Github: [链接] @Date: 2019-01-20 15:41:18 @LastEditTime: 2019-01-20 15:41:23--> 笔记地址 因为之前学习前端的收集书签的资源太多，所以就在今年3、4月开始抽空整理了所有的书签...",
    "url": "https://segmentfault.com/a/1190000020905116",
    "author": "RainyCG",
    "home_url": "https://segmentfault.com/u/rainycg",
    "votes": "62",
    "rank": 9
  },
  {
    "title": "基于 HTML5 + WebGL 的地铁站 3D 可视化系统",
    "description": "工业互联网，物联网，可视化等名词在我们现在信息化的大背景下已经是耳熟能详，日常生活的交通，出行，吃穿等可能都可以用信息化的方式来为我们表达，在传统的可视化监控领域，一般都是基于 Web SCADA 的前端技术...",
    "url": "https://segmentfault.com/a/1190000020947219",
    "author": "hightopo",
    "home_url": "https://segmentfault.com/u/hightopo",
    "votes": "11",
    "rank": 10
  },
  {
    "title": "前端面试每日3+1（周汇总2019.11.10）",
    "description": "《论语》，曾子曰：“吾日三省吾身”（我每天多次反省自己）。 前端面试每日3+1题，以面试题来驱动学习，每天进步一点！ 让努力成为一种习惯，让奋斗成为一种享受！相信 坚持 的力量！！！",
    "url": "https://segmentfault.com/a/1190000020957347",
    "author": "浪子神剑",
    "home_url": "https://segmentfault.com/u/haizlin",
    "votes": "2",
    "rank": 11
  },
  {
    "title": "可能是最全的 “文本溢出截断省略” 方案合集",
    "description": "在我们的日常开发工作中，文本溢出截断省略是很常见的一种需考虑的业务场景细节。看上去 “稀松平常” ，但在实现上却有不同的区分，是单行截断还是多行截断？多行的截断判断是基于行数还是基于高度？这些问题之下...",
    "url": "https://segmentfault.com/a/1190000020920000",
    "author": "政采云前端团队",
    "home_url": "https://segmentfault.com/u/zhengcaiyunqianduantuandui",
    "votes": "30",
    "rank": 12
  },
  {
    "title": "GitHub 年度报告解读丨Python 击败 Java，中国开源贡献排名第二，中国香港增速最高...",
    "description": "自 2007 年成立，GitHub 如今已经 12 年了。毫无疑问，它如今已经是全球影响力最大、最权威的开源社区。",
    "url": "https://segmentfault.com/a/1190000020946481",
    "author": "徐九",
    "home_url": "https://segmentfault.com/u/weepie",
    "votes": "9",
    "rank": 13
  },
  {
    "title": "深入理解ES6 Modules",
    "description": "当下， 我们几乎所有的项目都是基于 webpack、rollup 等构建工具进行开发的，模块化已经是常态。",
    "url": "https://segmentfault.com/a/1190000020946563",
    "author": "皮小蛋",
    "home_url": "https://segmentfault.com/u/scaukk",
    "votes": "11",
    "rank": 14
  },
  {
    "title": "浅谈前端面试",
    "description": "最近组里大佬出差，面试的任务落在了我这个小喽啰身上。作为一位中级工程师，让我面试高级工程师，我也是压力山大，只得硬着头皮上。这几天面试了许许多多人，感慨良多，不吐不快",
    "url": "https://segmentfault.com/a/1190000020949791",
    "author": "Runningfyy",
    "home_url": "https://segmentfault.com/u/yangkaiqiang",
    "votes": "8",
    "rank": 15
  },
  {
    "title": "推荐系统中模型训练及使用流程的标准化",
    "description": "文章作者：梁超 腾讯 高级工程师 编辑整理：Hoh Xil 内容来源：DataFun AI Talk 出品社区：DataFun 注：欢迎转载，转载请在留言区内留言。 导读：本次分享的主题为推荐系统中模型训练及使用流程的标准化。在整个...",
    "url": "https://segmentfault.com/a/1190000020945770",
    "author": "DataFun",
    "home_url": "https://segmentfault.com/u/datafun",
    "votes": "6",
    "rank": 16
  },
  {
    "title": "前端培训-中级阶段（25）-Web Socket 网络编程（2019-11-14期）",
    "description": "前端最基础的就是 HTML+CSS+Javascript。掌握了这三门技术就算入门，但也仅仅是入门，现在前端开发的定义已经远远不止这些。前端小课堂（HTML/CSS/JS），本着提升技术水平，打牢基础知识的中心思想，我们开课啦（...",
    "url": "https://segmentfault.com/a/1190000020933267",
    "author": "linong",
    "home_url": "https://segmentfault.com/u/linong",
    "votes": "10",
    "rank": 17
  },
  {
    "title": "全面拥抱React-Hooks",
    "description": "丑话说在前面 强烈建议至少刷一遍《官方文档》，反复研读《Hooks FAQ》这里主要以本人关注点聚合，方便理解用于实践 一、React-Hooks要解决什么？ 以下是上一代标准写法类组件的缺点，也正是hook要解决的问题 大...",
    "url": "https://segmentfault.com/a/1190000020948922",
    "author": "周振超",
    "home_url": "https://segmentfault.com/u/zhouzhenchao",
    "votes": "8",
    "rank": 18
  },
  {
    "title": "ES6 Promise",
    "description": "最近一段时间在重温ES6，Promise应该是是ES6新特性中非常重要的一部分内容。其实Promise在我日常开发中已经用得比较多，但大多数时候只是知道Promise可以用来实现异步编程，也只限于单纯地会用罢了，并没有时间深...",
    "url": "https://segmentfault.com/a/1190000020934044",
    "author": "云鱼Cloudy",
    "home_url": "https://segmentfault.com/u/cloudyttt",
    "votes": "15",
    "rank": 19
  },
  {
    "title": "Vue 3 中令人兴奋的新功能",
    "description": "在上一篇文章中，我们了解了 Vue 3 将带来的性能改进。我们已经知道，用新的 Vue 3 编写的程序效果会很好，但性能并不是最重要的部分。对开发人员而言，最重要的是新版本将会怎样影响我们编写代码的方式。",
    "url": "https://segmentfault.com/a/1190000020933028",
    "author": "疯狂的技术宅",
    "home_url": "https://segmentfault.com/u/evilboy",
    "votes": "16",
    "rank": 20
  },
  {
    "title": "获取鼠标位置（区分event对象中的 clientX、offsetX、screenX、pageX ）",
    "description": "client直译就是客户端，客户端的窗口就是指游览器的显示页面内容的窗口大小（不包含工具栏、导航栏等等）。",
    "url": "https://segmentfault.com/a/1190000020949241",
    "author": "教父的秘书",
    "home_url": "https://segmentfault.com/u/yaokai",
    "votes": "4",
    "rank": 21
  },
  {
    "title": "使用 Gitea 快速搭建私有 Git 版本控制服务",
    "description": "分布式版本控制工具 Git 已经是现代软件源代码版本控制首选方案之一。公有 Git 服务提供商 国外知名如 GitHub 国内网络延迟高,Gitlab 涉嫌对中国的歧视不推荐。国内有 Gitee、Coding 生态还不错。但是一般公司的...",
    "url": "https://segmentfault.com/a/1190000020948710",
    "author": "码农小胖哥",
    "home_url": "https://segmentfault.com/u/10000000",
    "votes": "5",
    "rank": 22
  },
  {
    "title": "React 中获取数据的 3 种方法：哪种最好？",
    "description": "上个月自己花了 1300 买了阿里的服务器来学习 node 及对应的框架，在 11 号之前它们有做活动，1300 的配置现在一年只要 86 元，三年只要229元，真心觉得很划算了，可以点击下面链接进行参与:",
    "url": "https://segmentfault.com/a/1190000020938724",
    "author": "前端小智",
    "home_url": "https://segmentfault.com/u/minnanitkong",
    "votes": "8",
    "rank": 23
  },
  {
    "title": "一工具让你的网站支持iOS13 Darkmode 模式",
    "description": "最近iOS13 发布了darkmode模式。虽然本人觉得次此功能呼声大于实际，但作为一个以用户体验为己任的前端，当然不能坐视不管，我们总该做点什么。",
    "url": "https://segmentfault.com/a/1190000020943959",
    "author": "fwon",
    "home_url": "https://segmentfault.com/u/fwon",
    "votes": "5",
    "rank": 24
  },
  {
    "title": "写给 Web 工程师的 DNS 知识入门",
    "description": "你是不是对 DNS 记录的一些概念不太了解，比如 A 记录、CNAME、AlIAS 等。。 下面让我们一起来学习一下~ 1 简介 为了访问 www.savokiss.com 这个域名，你的电脑需要知道服务器在网络中的位置。 这意味着：你的电...",
    "url": "https://segmentfault.com/a/1190000020947331",
    "author": "savokiss",
    "home_url": "https://segmentfault.com/u/savokiss",
    "votes": "4",
    "rank": 25
  },
  {
    "title": "python滑块验证码的破解",
    "description": "破解滑块验证码的思路主要有2种： 获得一张完整的背景图和一张有缺口的图片，两张图片进行像素上的一一对比，找出不一样的坐标。 获得一张有缺口的图片和需要验证的小图，两张图片进行二极化以及归一化，确定小图...",
    "url": "https://segmentfault.com/a/1190000020955506",
    "author": "我爱静静",
    "home_url": "https://segmentfault.com/u/woaijingjing",
    "votes": "2",
    "rank": 26
  },
  {
    "title": "基于区块链究竟可以做什么？",
    "description": "这几天，随着中央政治局内部学习的讲话内容公布，区块链再一次成为了公众的焦点，不仅迅速登上了各大媒体的头版头条，带动一直低迷的比特币大涨了40%，同时也连带拉动A股区块链相关概念股的行情。一夜间，区块链...",
    "url": "https://segmentfault.com/a/1190000020938068",
    "author": "TalkingData",
    "home_url": "https://segmentfault.com/u/talkingdata",
    "votes": "9",
    "rank": 27
  },
  {
    "title": "用etcd实现服务注册和发现",
    "description": "服务注册：同一service的所有节点注册到相同目录下，节点启动后将自己的信息注册到所属服务的目录中。",
    "url": "https://segmentfault.com/a/1190000020944777",
    "author": "KevinYan",
    "home_url": "https://segmentfault.com/u/kevinyan",
    "votes": "3",
    "rank": 28
  }
]