[
  {
    "title": "服务端渲染基础",
    "description": "一般而言大家提到“渲染”，可能会说：“凡是从服务器返回的 HTML 页面，均算作是服务端渲染。”这可能让不少人还是觉得迷惑，简单说渲染就是“数据”和“模板”拼接到一起。举个例子：我们前端开发最常见的一个场景，请...",
    "url": "https://segmentfault.com/a/1190000041076565",
    "author": "云叔_又拍云",
    "home_url": "https://segmentfault.com/u/yunshu_blog",
    "votes": "5",
    "rank": 1
  },
  {
    "title": "JZ-018-二叉树的镜像",
    "description": "二叉树的镜像题目描述操作给定的二叉树，将其变换为源二叉树的镜像。题目链接: 二叉树的镜像代码 {代码...} 【每日寄语】 世上最耀眼的光芒除了太阳还有你努力的模样。",
    "url": "https://segmentfault.com/a/1190000041077044",
    "author": "雄狮虎豹",
    "home_url": "https://segmentfault.com/u/xiongshihubao",
    "votes": "4",
    "rank": 2
  },
  {
    "title": "前端架构师破局技能，NodeJS 落地 WebSocket 实践",
    "description": "本文从网络协议，技术背景，安全和生产应用的方向，详细介绍 WebSocket 在 Node.js 中的落地实践。大纲预览本文介绍的内容包括以下方面：网络协议进化Socket.IO？ws 模块实现Express 集成WebSocket 实例消息广播...",
    "url": "https://segmentfault.com/a/1190000041075299",
    "author": "杨成功",
    "home_url": "https://segmentfault.com/u/ruidoc",
    "votes": "3",
    "rank": 3
  },
  {
    "title": "想知道一个20k级别前端在项目中是怎么使用LocalStorage的吗？",
    "description": "大家好，我是林三心，用最通俗的话，讲最难的知识点是我的座右铭，基础是进阶的前提是我的初心，今天就给大家唠一下嗑，讲一下，怎么样使用 localStorage、sessionStorage ，才能更规范，更高大上，更能让人眼前...",
    "url": "https://segmentfault.com/a/1190000041078633",
    "author": "Sunshine_Lin",
    "home_url": "https://segmentfault.com/u/user_ze46ouik",
    "votes": "2",
    "rank": 4
  },
  {
    "title": "WebView秒开方案探索",
    "description": "当我们加载一个网页时，并不是发送一个url请求所有的内容都下载下来了，而是除了主URL请求外，还有其他很多的请求，比如JS、CSS、图片等文件，每一个都是独立的请求，部分请求还是串行的，需要将这些资源文件下载...",
    "url": "https://segmentfault.com/a/1190000041075702",
    "author": "得物技术",
    "home_url": "https://segmentfault.com/u/dewujishu",
    "votes": "1",
    "rank": 5
  },
  {
    "title": "JavaScript 性能优化",
    "description": "垃圾回收内存管理JavaScript 没有提供操作内存的 API，一切内存操作都是自动的。申请使用释放何为垃圾对象不再被引用对象不能从根上访问到可达对象可以访问到的对象（引用、作用域链）标准是从根出发是否能被找到...",
    "url": "https://segmentfault.com/a/1190000041038578",
    "author": "我都说不要了",
    "home_url": "https://segmentfault.com/u/xiao_yang",
    "votes": "1",
    "rank": 6
  },
  {
    "title": "云原生运行时的下一个五年",
    "description": "文｜马振军（花名：古今 )在基础架构领域耕耘多年目前在蚂蚁集团中间件团队负责 MOSN、Layotto 等项目的开发工作校对｜卓与、齐天本文 9053 字 阅读 18 分钟｜前言｜在过去几年里，蚂蚁集团的基础设施进行了广受...",
    "url": "https://segmentfault.com/a/1190000041080221",
    "author": "SOFAStack",
    "home_url": "https://segmentfault.com/u/sofastack",
    "votes": "2",
    "rank": 7
  },
  {
    "title": "常用的上传和下载",
    "description": "后端下载目前返回的是ResponseEntity<byte[]>类型，尽量避免报错，否则前端需要另写函数捕捉报错信息，如果没有查到相关信息则返回空。",
    "url": "https://segmentfault.com/a/1190000041076548",
    "author": "Rebecca",
    "home_url": "https://segmentfault.com/u/rebecca_5d293098968f6",
    "votes": "1",
    "rank": 8
  },
  {
    "title": "想进大厂，这是你绕不过的门槛",
    "description": "第二，程序员面试必考察数据结构与算法，尤其是大厂，因为算法和数据结构最能体现一个人的基本功，基本功扎实的人，无论是做工程还是去做算法，都不会差到哪里去。",
    "url": "https://segmentfault.com/a/1190000041080713",
    "author": "先定一个小目标",
    "home_url": "https://segmentfault.com/u/5gz5hi3e",
    "votes": "1",
    "rank": 9
  },
  {
    "title": "设计模式——工厂模式",
    "description": "1. 工厂模式概述在工厂模式中，创建对象不会对外界暴露创建逻辑，而是通过使用一个共同的接口来获取新创建的对象。在工厂模式中，不需要外界手动创建一个实例，而是通过调用对象工厂的方法，返回该类的实例。比如...",
    "url": "https://segmentfault.com/a/1190000041080669",
    "author": "Zealf",
    "home_url": "https://segmentfault.com/u/zealf",
    "votes": "1",
    "rank": 10
  },
  {
    "title": "google-diff-match-patch文本内容对比的使用",
    "description": "项目里面用到了文本的对比功能，就用了下google-diff-match-patch，不过也是只用了文件对比功能。这里来看一下是怎么使用的。",
    "url": "https://segmentfault.com/a/1190000041079194",
    "author": "极致极简",
    "home_url": "https://segmentfault.com/u/xueyufeng",
    "votes": "1",
    "rank": 11
  },
  {
    "title": "TIOBE 12 月榜：C# 有望冲击“年度编程语言奖”，PHP 遗憾跌出前十",
    "description": "近日，TIOBE 公布了 12 月份编程语言指数排行榜。其中，Python、C、Java 依旧分列前三甲，而 PHP 已遗憾跌出前十，C# 或将有望冲击“TIOBE 年度编程语言奖”。",
    "url": "https://segmentfault.com/a/1190000041076701",
    "author": "MissD",
    "home_url": "https://segmentfault.com/u/d2ms1shh",
    "votes": "1",
    "rank": 12
  },
  {
    "title": "QCon-OPPO数据平台Cloud Lake 降本增效实践",
    "description": "OPPO从19年开始，用了两年时间，以K8S，容器化为核心，完成了公司混合云建设，并实现100%在线业务上云。OPPO的业务，目前覆盖国内，南亚，欧洲，美洲，在国内我们有自己的机房，在海外，更多是和公有云合作，有AW...",
    "url": "https://segmentfault.com/a/1190000041075271",
    "author": "OPPO数智技术",
    "home_url": "https://segmentfault.com/u/oppo_internet_tech",
    "votes": "1",
    "rank": 13
  },
  {
    "title": "产品经理天马行空，表格组件应对自如",
    "description": "前端表格组件，大概是pc端中使用最频繁的组件，也是产品经理(一般还兼理UE,EX)最能折腾的一个组件。 福兮祸兮，在折腾中磨炼了许多年后，表格组件成为我在圈内唯一敢用精通来形容的技术点。",
    "url": "https://segmentfault.com/a/1190000041078326",
    "author": "写个程序换个饼",
    "home_url": "https://segmentfault.com/u/shimuyidai",
    "votes": "1",
    "rank": 14
  },
  {
    "title": "Networking (II)",
    "description": "计算机网络重点概述（面试向）本篇文章主要是整理面试常问的问题七层协议7 application layer6 presentation layer5 session layer4 transport layer3 network layer2 link layer1 physical layerTCP三次握手1: c...",
    "url": "https://segmentfault.com/a/1190000041077205",
    "author": "Sophia",
    "home_url": "https://segmentfault.com/u/chenyingxi",
    "votes": "1",
    "rank": 15
  }
]