[
  {
    "full_name": "stashapp/stash",
    "language": "Go",
    "color": "#00ADD8",
    "description": "",
    "forked": "394",
    "stargazers_count": 3349,
    "todayStar": "290 stars today",
    "html_url": "https://github.com/stashapp/stash",
    "rank": 1
  },
  {
    "full_name": "mastodon/mastodon",
    "language": "Ruby",
    "color": "#701516",
    "description": "",
    "forked": "4854",
    "stargazers_count": 31850,
    "todayStar": "337 stars today",
    "html_url": "https://github.com/mastodon/mastodon",
    "rank": 2
  },
  {
    "full_name": "geohot/tinygrad",
    "language": "Python",
    "color": "#3572A5",
    "description": "",
    "forked": "760",
    "stargazers_count": 8044,
    "todayStar": "188 stars today",
    "html_url": "https://github.com/geohot/tinygrad",
    "rank": 3
  },
  {
    "full_name": "microsoft/PowerToys",
    "language": "C#",
    "color": "#178600",
    "description": "",
    "forked": "4636",
    "stargazers_count": 81134,
    "todayStar": "119 stars today",
    "html_url": "https://github.com/microsoft/PowerToys",
    "rank": 4
  },
  {
    "full_name": "alibaba/higress",
    "language": "C++",
    "color": "#f34b7d",
    "description": "",
    "forked": "28",
    "stargazers_count": 167,
    "todayStar": "74 stars today",
    "html_url": "https://github.com/alibaba/higress",
    "rank": 5
  },
  {
    "full_name": "NationalSecurityAgency/ghidra",
    "language": "Java",
    "color": "#b07219",
    "description": "",
    "forked": "4543",
    "stargazers_count": 35695,
    "todayStar": "83 stars today",
    "html_url": "https://github.com/NationalSecurityAgency/ghidra",
    "rank": 6
  },
  {
    "full_name": "jwasham/coding-interview-university",
    "language": "",
    "color": "",
    "description": "",
    "forked": "63687",
    "stargazers_count": 238118,
    "todayStar": "214 stars today",
    "html_url": "https://github.com/jwasham/coding-interview-university",
    "rank": 7
  },
  {
    "full_name": "huggingface/diffusion-models-class",
    "language": "",
    "color": "",
    "description": "",
    "forked": "5",
    "stargazers_count": 140,
    "todayStar": "19 stars today",
    "html_url": "https://github.com/huggingface/diffusion-models-class",
    "rank": 8
  },
  {
    "full_name": "tiangolo/typer",
    "language": "Python",
    "color": "#3572A5",
    "description": "",
    "forked": "373",
    "stargazers_count": 9188,
    "todayStar": "27 stars today",
    "html_url": "https://github.com/tiangolo/typer",
    "rank": 9
  },
  {
    "full_name": "spacedriveapp/spacedrive",
    "language": "Rust",
    "color": "#dea584",
    "description": "",
    "forked": "401",
    "stargazers_count": 15077,
    "todayStar": "25 stars today",
    "html_url": "https://github.com/spacedriveapp/spacedrive",
    "rank": 10
  },
  {
    "full_name": "Netflix/conductor",
    "language": "Java",
    "color": "#b07219",
    "description": "",
    "forked": "1435",
    "stargazers_count": 5612,
    "todayStar": "115 stars today",
    "html_url": "https://github.com/Netflix/conductor",
    "rank": 11
  },
  {
    "full_name": "Budibase/budibase",
    "language": "JavaScript",
    "color": "#f1e05a",
    "description": "",
    "forked": "936",
    "stargazers_count": 15795,
    "todayStar": "67 stars today",
    "html_url": "https://github.com/Budibase/budibase",
    "rank": 12
  },
  {
    "full_name": "LSPosed/MagiskOnWSALocal",
    "language": "Shell",
    "color": "#89e051",
    "description": "",
    "forked": "7773",
    "stargazers_count": 2632,
    "todayStar": "22 stars today",
    "html_url": "https://github.com/LSPosed/MagiskOnWSALocal",
    "rank": 13
  },
  {
    "full_name": "mdn/content",
    "language": "Markdown",
    "color": "#083fa1",
    "description": "",
    "forked": "12915",
    "stargazers_count": 6662,
    "todayStar": "14 stars today",
    "html_url": "https://github.com/mdn/content",
    "rank": 14
  },
  {
    "full_name": "rocketseat-education/nlw-copa-ignite",
    "language": "TypeScript",
    "color": "#3178c6",
    "description": "",
    "forked": "21",
    "stargazers_count": 36,
    "todayStar": "8 stars today",
    "html_url": "https://github.com/rocketseat-education/nlw-copa-ignite",
    "rank": 15
  },
  {
    "full_name": "pi-hole/pi-hole",
    "language": "Shell",
    "color": "#89e051",
    "description": "",
    "forked": "2388",
    "stargazers_count": 39336,
    "todayStar": "20 stars today",
    "html_url": "https://github.com/pi-hole/pi-hole",
    "rank": 16
  },
  {
    "full_name": "halfrost/LeetCode-Go",
    "language": "Go",
    "color": "#00ADD8",
    "description": "",
    "forked": "5089",
    "stargazers_count": 27948,
    "todayStar": "49 stars today",
    "html_url": "https://github.com/halfrost/LeetCode-Go",
    "rank": 17
  },
  {
    "full_name": "Ehviewer-Overhauled/Ehviewer",
    "language": "Java",
    "color": "#b07219",
    "description": "",
    "forked": "40",
    "stargazers_count": 883,
    "todayStar": "40 stars today",
    "html_url": "https://github.com/Ehviewer-Overhauled/Ehviewer",
    "rank": 18
  },
  {
    "full_name": "microsoft/winget-cli",
    "language": "C++",
    "color": "#f34b7d",
    "description": "",
    "forked": "1060",
    "stargazers_count": 18090,
    "todayStar": "14 stars today",
    "html_url": "https://github.com/microsoft/winget-cli",
    "rank": 19
  },
  {
    "full_name": "commaai/openpilot",
    "language": "Python",
    "color": "#3572A5",
    "description": "",
    "forked": "6725",
    "stargazers_count": 36708,
    "todayStar": "113 stars today",
    "html_url": "https://github.com/commaai/openpilot",
    "rank": 20
  },
  {
    "full_name": "lidangzzz/How-to-run",
    "language": "TypeScript",
    "color": "#3178c6",
    "description": "",
    "forked": "178",
    "stargazers_count": 2747,
    "todayStar": "64 stars today",
    "html_url": "https://github.com/lidangzzz/How-to-run",
    "rank": 21
  },
  {
    "full_name": "home-assistant/core",
    "language": "Python",
    "color": "#3572A5",
    "description": "",
    "forked": "20341",
    "stargazers_count": 55693,
    "todayStar": "34 stars today",
    "html_url": "https://github.com/home-assistant/core",
    "rank": 22
  },
  {
    "full_name": "pygame/pygame",
    "language": "C",
    "color": "#555555",
    "description": "",
    "forked": "2355",
    "stargazers_count": 5354,
    "todayStar": "4 stars today",
    "html_url": "https://github.com/pygame/pygame",
    "rank": 23
  },
  {
    "full_name": "pi-hole/docker-pi-hole",
    "language": "Shell",
    "color": "#89e051",
    "description": "",
    "forked": "992",
    "stargazers_count": 5767,
    "todayStar": "12 stars today",
    "html_url": "https://github.com/pi-hole/docker-pi-hole",
    "rank": 24
  },
  {
    "full_name": "surrealdb/surrealdb",
    "language": "Rust",
    "color": "#dea584",
    "description": "",
    "forked": "343",
    "stargazers_count": 14914,
    "todayStar": "163 stars today",
    "html_url": "https://github.com/surrealdb/surrealdb",
    "rank": 25
  }
]